  <scheduller>
      <observation>
          <duration>
              <begin>1627110000</begin>
              <end>1627196340</end>
          </duration>
          <telescope>
              <latitude>32.7015</latitude>
              <longitude>-109.891284</longitude>
              <altitude>3185</altitude>
              <velocity>
                  <ra>0.5</ra>
                  <dec>0.6</dec>
              </velocity>
          </telescope>
          <elevation>
              <minimal>30</minimal>
              <maximal>80</maximal>
          </elevation>
          <escape>
              <sun>23</sun>
          </escape>
      </observation>
      <sources>
          <object>
              <identifier>&#xA;&#x9;&#x9;&#x9;&#x9;J2225+6535&#xA;&#x9;&#x9;&#x9;</identifier>
              <ra>336.468</ra>
              <dec>65.5927</dec>
              <duration>0</duration>
              <weight>1</weight>
              <important>0</important>
              <Rises>1627110000</Rises>
              <Rises>1627140600</Rises>
              <Rises>1627184400</Rises>
              <Rises>1627196340</Rises>
              <SortMark>false</SortMark>
              <Schedule>
                  <Scheduled>true</Scheduled>
                  <Key>73</Key>
                  <Duration>1627110000</Duration>
                  <Duration>1627110000</Duration>
                  <Gap>0</Gap>
              </Schedule>
          </object>
          <object>
              <identifier>&#xA;&#x9;&#x9;&#x9;&#x9;J2046+1540&#xA;&#x9;&#x9;&#x9;</identifier>
              <ra>311.664</ra>
              <dec>15.676</dec>
              <duration>0</duration>
              <weight>1</weight>
              <important>0</important>
              <Rises>1627110000</Rises>
              <Rises>1627128900</Rises>
              <Rises>1627184400</Rises>
              <Rises>1627196340</Rises>
              <SortMark>false</SortMark>
              <Schedule>
                  <Scheduled>true</Scheduled>
                  <Key>72</Key>
                  <Duration>1627110000</Duration>
                  <Duration>1627110000</Duration>
                  <Gap>83</Gap>
              </Schedule>
          </object>
          <object>
              <identifier>&#xA;&#x9;&#x9;&#x9;&#x9;J1840+5640&#xA;&#x9;&#x9;&#x9;</identifier>
              <ra>280.186</ra>
              <dec>56.6821</dec>
              <duration>0</duration>
              <weight>1</weight>
              <important>0</important>
              <Rises>1627110000</Rises>
              <Rises>1627126200</Rises>
              <Rises>1627172100</Rises>
              <Rises>1627196340</Rises>
              <SortMark>false</SortMark>
              <Schedule>
                  <Scheduled>true</Scheduled>
                  <Key>71</Key>
                  <Duration>1627110083</Duration>
                  <Duration>1627110083</Duration>
                  <Gap>68</Gap>
              </Schedule>
          </object>
          <object>
              <identifier>&#xA;&#x9;&#x9;&#x9;&#x9;J2022+5154&#xA;&#x9;&#x9;&#x9;</identifier>
              <ra>305.708</ra>
              <dec>51.914</dec>
              <duration>0</duration>
              <weight>1</weight>
              <important>0</important>
              <Rises>1627110000</Rises>
              <Rises>1627131600</Rises>
              <Rises>1627178700</Rises>
              <Rises>1627196340</Rises>
              <SortMark>false</SortMark>
              <Schedule>
                  <Scheduled>true</Scheduled>
                  <Key>70</Key>
                  <Duration>1627110151</Duration>
                  <Duration>1627110151</Duration>
                  <Gap>51</Gap>
              </Schedule>
          </object>
          <object>
              <identifier>&#xA;&#x9;&#x9;&#x9;&#x9;J2317+1439&#xA;&#x9;&#x9;&#x9;</identifier>
              <ra>349.288</ra>
              <dec>14.6587</dec>
              <duration>0</duration>
              <weight>1</weight>
              <important>0</important>
              <Rises>1627110000</Rises>
              <Rises>1627137900</Rises>
              <Rises>1627193700</Rises>
              <Rises>1627196340</Rises>
              <SortMark>false</SortMark>
              <Schedule>
                  <Scheduled>true</Scheduled>
                  <Key>69</Key>
                  <Duration>1627110202</Duration>
                  <Duration>1627110202</Duration>
                  <Gap>87</Gap>
              </Schedule>
          </object>
          <object>
              <identifier>&#xA;&#x9;&#x9;&#x9;&#x9;J1911-1114&#xA;&#x9;&#x9;&#x9;</identifier>
              <ra>287.955</ra>
              <dec>-11.2395</dec>
              <duration>0</duration>
              <weight>1</weight>
              <important>0</important>
              <Rises>1627110000</Rises>
              <Rises>1627118100</Rises>
              <Rises>1627183800</Rises>
              <Rises>1627196340</Rises>
              <SortMark>false</SortMark>
              <Schedule>
                  <Scheduled>true</Scheduled>
                  <Key>65</Key>
                  <Duration>1627110289</Duration>
                  <Duration>1627110289</Duration>
                  <Gap>122</Gap>
              </Schedule>
          </object>
          <object>
              <identifier>&#xA;&#x9;&#x9;&#x9;&#x9;J1913-0440&#xA;&#x9;&#x9;&#x9;</identifier>
              <ra>288.476</ra>
              <dec>-4.67989</dec>
              <duration>0</duration>
              <weight>1</weight>
              <important>0</important>
              <Rises>1627110000</Rises>
              <Rises>1627119900</Rises>
              <Rises>1627182300</Rises>
              <Rises>1627196340</Rises>
              <SortMark>false</SortMark>
              <Schedule>
                  <Scheduled>true</Scheduled>
                  <Key>64</Key>
                  <Duration>1627110411</Duration>
                  <Duration>1627110411</Duration>
                  <Gap>10</Gap>
              </Schedule>
          </object>
          <object>
              <identifier>&#xA;&#x9;&#x9;&#x9;&#x9;J2157+4017&#xA;&#x9;&#x9;&#x9;</identifier>
              <ra>329.258</ra>
              <dec>40.2961</dec>
              <duration>0</duration>
              <weight>1</weight>
              <important>0</important>
              <Rises>1627110000</Rises>
              <Rises>1627115700</Rises>
              <Rises>1627119600</Rises>
              <Rises>1627136100</Rises>
              <Rises>1627185600</Rises>
              <Rises>1627196340</Rises>
              <SortMark>false</SortMark>
              <Schedule>
                  <Scheduled>true</Scheduled>
                  <Key>59</Key>
                  <Duration>1627110421</Duration>
                  <Duration>1627110421</Duration>
                  <Gap>81</Gap>
              </Schedule>
          </object>
          <object>
              <identifier>&#xA;&#x9;&#x9;&#x9;&#x9;J2113+4644&#xA;&#x9;&#x9;&#x9;</identifier>
              <ra>318.351</ra>
              <dec>46.7357</dec>
              <duration>0</duration>
              <weight>1</weight>
              <important>0</important>
              <Rises>1627110000</Rises>
              <Rises>1627134300</Rises>
              <Rises>1627182300</Rises>
              <Rises>1627196340</Rises>
              <SortMark>false</SortMark>
              <Schedule>
                  <Scheduled>true</Scheduled>
                  <Key>58</Key>
                  <Duration>1627110502</Duration>
                  <Duration>1627110502</Duration>
                  <Gap>21</Gap>
              </Schedule>
          </object>
          <object>
              <identifier>&#xA;&#x9;&#x9;&#x9;&#x9;J2113+2754&#xA;&#x9;&#x9;&#x9;</identifier>
              <ra>318.268</ra>
              <dec>27.9006</dec>
              <duration>0</duration>
              <weight>1</weight>
              <important>0</important>
              <Rises>1627110000</Rises>
              <Rises>1627112700</Rises>
              <Rises>1627117500</Rises>
              <Rises>1627132200</Rises>
              <Rises>1627184400</Rises>
              <Rises>1627196340</Rises>
              <SortMark>false</SortMark>
              <Schedule>
                  <Scheduled>true</Scheduled>
                  <Key>57</Key>
                  <Duration>1627110523</Duration>
                  <Duration>1627110523</Duration>
                  <Gap>31</Gap>
              </Schedule>
          </object>
          <object>
              <identifier>&#xA;&#x9;&#x9;&#x9;&#x9;J2046-0421&#xA;&#x9;&#x9;&#x9;</identifier>
              <ra>311.501</ra>
              <dec>-4.35719</dec>
              <duration>0</duration>
              <weight>1</weight>
              <important>0</important>
              <Rises>1627110000</Rises>
              <Rises>1627125600</Rises>
              <Rises>1627187700</Rises>
              <Rises>1627196340</Rises>
              <SortMark>false</SortMark>
              <Schedule>
                  <Scheduled>true</Scheduled>
                  <Key>55</Key>
                  <Duration>1627110554</Duration>
                  <Duration>1627110554</Duration>
                  <Gap>53</Gap>
              </Schedule>
          </object>
          <object>
              <identifier>&#xA;&#x9;&#x9;&#x9;&#x9;J2145-0750&#xA;&#x9;&#x9;&#x9;</identifier>
              <ra>326.46</ra>
              <dec>-7.8385</dec>
              <duration>0</duration>
              <weight>1</weight>
              <important>0</important>
              <Rises>1627110000</Rises>
              <Rises>1627128300</Rises>
              <Rises>1627192200</Rises>
              <Rises>1627196340</Rises>
              <SortMark>false</SortMark>
              <Schedule>
                  <Scheduled>true</Scheduled>
                  <Key>54</Key>
                  <Duration>1627110607</Duration>
                  <Duration>1627110607</Duration>
                  <Gap>29</Gap>
              </Schedule>
          </object>
          <object>
              <identifier>&#xA;&#x9;&#x9;&#x9;&#x9;J2051-0827&#xA;&#x9;&#x9;&#x9;</identifier>
              <ra>312.781</ra>
              <dec>-8.4605</dec>
              <duration>0</duration>
              <weight>1</weight>
              <important>0</important>
              <Rises>1627110000</Rises>
              <Rises>1627124700</Rises>
              <Rises>1627188900</Rises>
              <Rises>1627196340</Rises>
              <SortMark>false</SortMark>
              <Schedule>
                  <Scheduled>true</Scheduled>
                  <Key>53</Key>
                  <Duration>1627110636</Duration>
                  <Duration>1627110636</Duration>
                  <Gap>27</Gap>
              </Schedule>
          </object>
          <object>
              <identifier>&#xA;&#x9;&#x9;&#x9;&#x9;J2145-0750&#xA;&#x9;&#x9;&#x9;</identifier>
              <ra>326.46</ra>
              <dec>-7.8385</dec>
              <duration>0</duration>
              <weight>1</weight>
              <important>0</important>
              <Rises>1627110000</Rises>
              <Rises>1627128300</Rises>
              <Rises>1627192200</Rises>
              <Rises>1627196340</Rises>
              <SortMark>false</SortMark>
              <Schedule>
                  <Scheduled>true</Scheduled>
                  <Key>52</Key>
                  <Duration>1627110663</Duration>
                  <Duration>1627110663</Duration>
                  <Gap>27</Gap>
              </Schedule>
          </object>
          <object>
              <identifier>&#xA;&#x9;&#x9;&#x9;&#x9;J1939+2134&#xA;&#x9;&#x9;&#x9;</identifier>
              <ra>294.915</ra>
              <dec>21.6227</dec>
              <duration>0</duration>
              <weight>1</weight>
              <important>0</important>
              <Rises>1627110000</Rises>
              <Rises>1627125600</Rises>
              <Rises>1627179600</Rises>
              <Rises>1627196340</Rises>
              <SortMark>false</SortMark>
              <Schedule>
                  <Scheduled>true</Scheduled>
                  <Key>51</Key>
                  <Duration>1627110690</Duration>
                  <Duration>1627110690</Duration>
                  <Gap>63</Gap>
              </Schedule>
          </object>
          <object>
              <identifier>&#xA;&#x9;&#x9;&#x9;&#x9;J2313+4253&#xA;&#x9;&#x9;&#x9;</identifier>
              <ra>348.286</ra>
              <dec>42.8869</dec>
              <duration>0</duration>
              <weight>1</weight>
              <important>0</important>
              <Rises>1627110000</Rises>
              <Rises>1627140900</Rises>
              <Rises>1627189800</Rises>
              <Rises>1627196340</Rises>
              <SortMark>false</SortMark>
              <Schedule>
                  <Scheduled>true</Scheduled>
                  <Key>49</Key>
                  <Duration>1627110753</Duration>
                  <Duration>1627110753</Duration>
                  <Gap>106</Gap>
              </Schedule>
          </object>
          <object>
              <identifier>&#xA;&#x9;&#x9;&#x9;&#x9;J2326+6113&#xA;&#x9;&#x9;&#x9;</identifier>
              <ra>351.745</ra>
              <dec>61.2268</dec>
              <duration>0</duration>
              <weight>1</weight>
              <important>0</important>
              <Rises>1627110000</Rises>
              <Rises>1627143900</Rises>
              <Rises>1627188600</Rises>
              <Rises>1627196340</Rises>
              <SortMark>false</SortMark>
              <Schedule>
                  <Scheduled>true</Scheduled>
                  <Key>48</Key>
                  <Duration>1627110859</Duration>
                  <Duration>1627110859</Duration>
                  <Gap>30</Gap>
              </Schedule>
          </object>
          <object>
              <identifier>&#xA;&#x9;&#x9;&#x9;&#x9;J2326+6113&#xA;&#x9;&#x9;&#x9;</identifier>
              <ra>351.745</ra>
              <dec>61.2268</dec>
              <duration>0</duration>
              <weight>1</weight>
              <important>0</important>
              <Rises>1627110000</Rises>
              <Rises>1627143900</Rises>
              <Rises>1627188600</Rises>
              <Rises>1627196340</Rises>
              <SortMark>false</SortMark>
              <Schedule>
                  <Scheduled>true</Scheduled>
                  <Key>47</Key>
                  <Duration>1627110889</Duration>
                  <Duration>1627110889</Duration>
                  <Gap>0</Gap>
              </Schedule>
          </object>
          <object>
              <identifier>&#xA;&#x9;&#x9;&#x9;&#x9;J2305+3100&#xA;&#x9;&#x9;&#x9;</identifier>
              <ra>346.493</ra>
              <dec>31.0005</dec>
              <duration>0</duration>
              <weight>1</weight>
              <important>0</important>
              <Rises>1627110000</Rises>
              <Rises>1627119000</Rises>
              <Rises>1627124700</Rises>
              <Rises>1627139100</Rises>
              <Rises>1627190700</Rises>
              <Rises>1627196340</Rises>
              <SortMark>false</SortMark>
              <Schedule>
                  <Scheduled>true</Scheduled>
                  <Key>46</Key>
                  <Duration>1627110889</Duration>
                  <Duration>1627110889</Duration>
                  <Gap>50</Gap>
              </Schedule>
          </object>
          <object>
              <identifier>&#xA;&#x9;&#x9;&#x9;&#x9;J2317+2149&#xA;&#x9;&#x9;&#x9;</identifier>
              <ra>349.491</ra>
              <dec>21.83</dec>
              <duration>0</duration>
              <weight>1</weight>
              <important>0</important>
              <Rises>1627110000</Rises>
              <Rises>1627138800</Rises>
              <Rises>1627192500</Rises>
              <Rises>1627196340</Rises>
              <SortMark>false</SortMark>
              <Schedule>
                  <Scheduled>true</Scheduled>
                  <Key>45</Key>
                  <Duration>1627110939</Duration>
                  <Duration>1627110939</Duration>
                  <Gap>15</Gap>
              </Schedule>
          </object>
          <object>
              <identifier>&#xA;&#x9;&#x9;&#x9;&#x9;J2317+1439&#xA;&#x9;&#x9;&#x9;</identifier>
              <ra>349.288</ra>
              <dec>14.6587</dec>
              <duration>0</duration>
              <weight>1</weight>
              <important>0</important>
              <Rises>1627110000</Rises>
              <Rises>1627137900</Rises>
              <Rises>1627193700</Rises>
              <Rises>1627196340</Rises>
              <SortMark>false</SortMark>
              <Schedule>
                  <Scheduled>true</Scheduled>
                  <Key>44</Key>
                  <Duration>1627110954</Duration>
                  <Duration>1627110954</Duration>
                  <Gap>11</Gap>
              </Schedule>
          </object>
          <object>
              <identifier>&#xA;&#x9;&#x9;&#x9;&#x9;J2048-1616&#xA;&#x9;&#x9;&#x9;</identifier>
              <ra>312.149</ra>
              <dec>-16.2797</dec>
              <duration>0</duration>
              <weight>1</weight>
              <important>0</important>
              <Rises>1627110000</Rises>
              <Rises>1627122300</Rises>
              <Rises>1627191300</Rises>
              <Rises>1627196340</Rises>
              <SortMark>false</SortMark>
              <Schedule>
                  <Scheduled>true</Scheduled>
                  <Key>43</Key>
                  <Duration>1627110965</Duration>
                  <Duration>1627110965</Duration>
                  <Gap>74</Gap>
              </Schedule>
          </object>
          <object>
              <identifier>&#xA;&#x9;&#x9;&#x9;&#x9;J2048–1616&#xA;&#x9;&#x9;&#x9;</identifier>
              <ra>312.149</ra>
              <dec>-16.2797</dec>
              <duration>0</duration>
              <weight>1</weight>
              <important>0</important>
              <Rises>1627110000</Rises>
              <Rises>1627122300</Rises>
              <Rises>1627191300</Rises>
              <Rises>1627196340</Rises>
              <SortMark>false</SortMark>
              <Schedule>
                  <Scheduled>true</Scheduled>
                  <Key>42</Key>
                  <Duration>1627111039</Duration>
                  <Duration>1627111039</Duration>
                  <Gap>0</Gap>
              </Schedule>
          </object>
          <object>
              <identifier>&#xA;&#x9;&#x9;&#x9;&#x9;J1935+1616&#xA;&#x9;&#x9;&#x9;</identifier>
              <ra>293.949</ra>
              <dec>16.2778</dec>
              <duration>0</duration>
              <weight>1</weight>
              <important>0</important>
              <Rises>1627110000</Rises>
              <Rises>1627124700</Rises>
              <Rises>1627180200</Rises>
              <Rises>1627196340</Rises>
              <SortMark>false</SortMark>
              <Schedule>
                  <Scheduled>true</Scheduled>
                  <Key>41</Key>
                  <Duration>1627111039</Duration>
                  <Duration>1627111039</Duration>
                  <Gap>54</Gap>
              </Schedule>
          </object>
          <object>
              <identifier>&#xA;&#x9;&#x9;&#x9;&#x9;J1917+1353&#xA;&#x9;&#x9;&#x9;</identifier>
              <ra>289.416</ra>
              <dec>13.8992</dec>
              <duration>0</duration>
              <weight>1</weight>
              <important>0</important>
              <Rises>1627110000</Rises>
              <Rises>1627123200</Rises>
              <Rises>1627179300</Rises>
              <Rises>1627196340</Rises>
              <SortMark>false</SortMark>
              <Schedule>
                  <Scheduled>true</Scheduled>
                  <Key>40</Key>
                  <Duration>1627111093</Duration>
                  <Duration>1627111093</Duration>
                  <Gap>9</Gap>
              </Schedule>
          </object>
          <object>
              <identifier>&#xA;&#x9;&#x9;&#x9;&#x9;J1932+1059&#xA;&#x9;&#x9;&#x9;</identifier>
              <ra>293.059</ra>
              <dec>10.9926</dec>
              <duration>0</duration>
              <weight>1</weight>
              <important>0</important>
              <Rises>1627110000</Rises>
              <Rises>1627123800</Rises>
              <Rises>1627180500</Rises>
              <Rises>1627196340</Rises>
              <SortMark>false</SortMark>
              <Schedule>
                  <Scheduled>true</Scheduled>
                  <Key>39</Key>
                  <Duration>1627111102</Duration>
                  <Duration>1627111102</Duration>
                  <Gap>7</Gap>
              </Schedule>
          </object>
          <object>
              <identifier>&#xA;&#x9;&#x9;&#x9;&#x9;J1713+0747&#xA;&#x9;&#x9;&#x9;</identifier>
              <ra>258.456</ra>
              <dec>7.79376</dec>
              <duration>0</duration>
              <weight>1</weight>
              <important>0</important>
              <Rises>1627110000</Rises>
              <Rises>1627115100</Rises>
              <Rises>1627172700</Rises>
              <Rises>1627196340</Rises>
              <SortMark>false</SortMark>
              <Schedule>
                  <Scheduled>true</Scheduled>
                  <Key>38</Key>
                  <Duration>1627111109</Duration>
                  <Duration>1627111109</Duration>
                  <Gap>69</Gap>
              </Schedule>
          </object>
          <object>
              <identifier>&#xA;&#x9;&#x9;&#x9;&#x9;J1713+0747&#xA;&#x9;&#x9;&#x9;</identifier>
              <ra>258.456</ra>
              <dec>7.79376</dec>
              <duration>0</duration>
              <weight>1</weight>
              <important>0</important>
              <Rises>1627110000</Rises>
              <Rises>1627115100</Rises>
              <Rises>1627172700</Rises>
              <Rises>1627196340</Rises>
              <SortMark>false</SortMark>
              <Schedule>
                  <Scheduled>true</Scheduled>
                  <Key>37</Key>
                  <Duration>1627111178</Duration>
                  <Duration>1627111178</Duration>
                  <Gap>0</Gap>
              </Schedule>
          </object>
          <object>
              <identifier>&#xA;&#x9;&#x9;&#x9;&#x9;J1741-0840&#xA;&#x9;&#x9;&#x9;</identifier>
              <ra>265.344</ra>
              <dec>-8.6755</dec>
              <duration>0</duration>
              <weight>1</weight>
              <important>0</important>
              <Rises>1627110000</Rises>
              <Rises>1627113300</Rises>
              <Rises>1627177800</Rises>
              <Rises>1627196340</Rises>
              <SortMark>false</SortMark>
              <Schedule>
                  <Scheduled>true</Scheduled>
                  <Key>36</Key>
                  <Duration>1627111178</Duration>
                  <Duration>1627111178</Duration>
                  <Gap>27</Gap>
              </Schedule>
          </object>
          <object>
              <identifier>&#xA;&#x9;&#x9;&#x9;&#x9;J1744-1134&#xA;&#x9;&#x9;&#x9;</identifier>
              <ra>266.123</ra>
              <dec>-11.5819</dec>
              <duration>0</duration>
              <weight>1</weight>
              <important>0</important>
              <Rises>1627110000</Rises>
              <Rises>1627112700</Rises>
              <Rises>1627178700</Rises>
              <Rises>1627196340</Rises>
              <SortMark>false</SortMark>
              <Schedule>
                  <Scheduled>true</Scheduled>
                  <Key>31</Key>
                  <Duration>1627111205</Duration>
                  <Duration>1627111205</Duration>
                  <Gap>4</Gap>
              </Schedule>
          </object>
          <object>
              <identifier>&#xA;&#x9;&#x9;&#x9;&#x9;J1744–1134&#xA;&#x9;&#x9;&#x9;</identifier>
              <ra>266.123</ra>
              <dec>-11.5819</dec>
              <duration>0</duration>
              <weight>1</weight>
              <important>0</important>
              <Rises>1627110000</Rises>
              <Rises>1627112700</Rises>
              <Rises>1627178700</Rises>
              <Rises>1627196340</Rises>
              <SortMark>false</SortMark>
              <Schedule>
                  <Scheduled>true</Scheduled>
                  <Key>30</Key>
                  <Duration>1627111209</Duration>
                  <Duration>1627111209</Duration>
                  <Gap>0</Gap>
              </Schedule>
          </object>
          <object>
              <identifier>&#xA;&#x9;&#x9;&#x9;&#x9;J1820-0427&#xA;&#x9;&#x9;&#x9;</identifier>
              <ra>275.219</ra>
              <dec>-4.46031</dec>
              <duration>0</duration>
              <weight>1</weight>
              <important>0</important>
              <Rises>1627110000</Rises>
              <Rises>1627116900</Rises>
              <Rises>1627179000</Rises>
              <Rises>1627196340</Rises>
              <SortMark>false</SortMark>
              <Schedule>
                  <Scheduled>true</Scheduled>
                  <Key>29</Key>
                  <Duration>1627111209</Duration>
                  <Duration>1627111209</Duration>
                  <Gap>18</Gap>
              </Schedule>
          </object>
          <object>
              <identifier>&#xA;&#x9;&#x9;&#x9;&#x9;J1807-0847&#xA;&#x9;&#x9;&#x9;</identifier>
              <ra>271.908</ra>
              <dec>-8.79535</dec>
              <duration>0</duration>
              <weight>1</weight>
              <important>0</important>
              <Rises>1627110000</Rises>
              <Rises>1627115100</Rises>
              <Rises>1627179300</Rises>
              <Rises>1627196340</Rises>
              <SortMark>false</SortMark>
              <Schedule>
                  <Scheduled>true</Scheduled>
                  <Key>28</Key>
                  <Duration>1627111227</Duration>
                  <Duration>1627111227</Duration>
                  <Gap>7</Gap>
              </Schedule>
          </object>
          <object>
              <identifier>&#xA;&#x9;&#x9;&#x9;&#x9;J1807-0847&#xA;&#x9;&#x9;&#x9;</identifier>
              <ra>271.908</ra>
              <dec>-8.79535</dec>
              <duration>0</duration>
              <weight>1</weight>
              <important>0</important>
              <Rises>1627110000</Rises>
              <Rises>1627115100</Rises>
              <Rises>1627179300</Rises>
              <Rises>1627196340</Rises>
              <SortMark>false</SortMark>
              <Schedule>
                  <Scheduled>true</Scheduled>
                  <Key>27</Key>
                  <Duration>1627111234</Duration>
                  <Duration>1627111234</Duration>
                  <Gap>0</Gap>
              </Schedule>
          </object>
          <object>
              <identifier>&#xA;&#x9;&#x9;&#x9;&#x9;J1509+5531&#xA;&#x9;&#x9;&#x9;</identifier>
              <ra>227.357</ra>
              <dec>55.5258</dec>
              <duration>0</duration>
              <weight>1</weight>
              <important>0</important>
              <Rises>1627110000</Rises>
              <Rises>1627113300</Rises>
              <Rises>1627159500</Rises>
              <Rises>1627196340</Rises>
              <SortMark>false</SortMark>
              <Schedule>
                  <Scheduled>true</Scheduled>
                  <Key>24</Key>
                  <Duration>1627111234</Duration>
                  <Duration>1627111234</Duration>
                  <Gap>107</Gap>
              </Schedule>
          </object>
          <object>
              <identifier>&#xA;&#x9;&#x9;&#x9;&#x9;J1532+2745&#xA;&#x9;&#x9;&#x9;</identifier>
              <ra>233.043</ra>
              <dec>27.7637</dec>
              <duration>0</duration>
              <weight>1</weight>
              <important>0</important>
              <Rises>1627110000</Rises>
              <Rises>1627111500</Rises>
              <Rises>1627164000</Rises>
              <Rises>1627178400</Rises>
              <Rises>1627183200</Rises>
              <Rises>1627196340</Rises>
              <SortMark>false</SortMark>
              <Schedule>
                  <Scheduled>true</Scheduled>
                  <Key>23</Key>
                  <Duration>1627111341</Duration>
                  <Duration>1627111341</Duration>
                  <Gap>46</Gap>
              </Schedule>
          </object>
          <object>
              <identifier>&#xA;&#x9;&#x9;&#x9;&#x9;J1640+2224&#xA;&#x9;&#x9;&#x9;</identifier>
              <ra>250.07</ra>
              <dec>22.4025</dec>
              <duration>0</duration>
              <weight>1</weight>
              <important>0</important>
              <Rises>1627110000</Rises>
              <Rises>1627115100</Rises>
              <Rises>1627168800</Rises>
              <Rises>1627196340</Rises>
              <SortMark>false</SortMark>
              <Schedule>
                  <Scheduled>true</Scheduled>
                  <Key>22</Key>
                  <Duration>1627111387</Duration>
                  <Duration>1627111387</Duration>
                  <Gap>34</Gap>
              </Schedule>
          </object>
          <object>
              <identifier>&#xA;&#x9;&#x9;&#x9;&#x9;J2006-0807&#xA;&#x9;&#x9;&#x9;</identifier>
              <ra>301.568</ra>
              <dec>-8.11694</dec>
              <duration>0</duration>
              <weight>1</weight>
              <important>0</important>
              <Rises>1627110000</Rises>
              <Rises>1627122300</Rises>
              <Rises>1627186200</Rises>
              <Rises>1627196340</Rises>
              <SortMark>false</SortMark>
              <Schedule>
                  <Scheduled>true</Scheduled>
                  <Key>0</Key>
                  <Duration>1627111421</Duration>
                  <Duration>1627111421</Duration>
                  <Gap>102</Gap>
              </Schedule>
          </object>
          <object>
              <identifier>&#xA;&#x9;&#x9;&#x9;&#x9;J2346-0610&#xA;&#x9;&#x9;&#x9;</identifier>
              <ra>356.71</ra>
              <dec>-6.16694</dec>
              <duration>0</duration>
              <weight>1</weight>
              <important>0</important>
              <Rises>1627112700</Rises>
              <Rises>1627135800</Rises>
              <SortMark>false</SortMark>
              <Schedule>
                  <Scheduled>true</Scheduled>
                  <Key>35</Key>
                  <Duration>1627112723</Duration>
                  <Duration>1627112723</Duration>
                  <Gap>110</Gap>
              </Schedule>
          </object>
          <object>
              <identifier>&#xA;&#x9;&#x9;&#x9;&#x9;J2018+2839&#xA;&#x9;&#x9;&#x9;</identifier>
              <ra>304.516</ra>
              <dec>28.6653</dec>
              <duration>0</duration>
              <weight>1</weight>
              <important>0</important>
              <Rises>1627114500</Rises>
              <Rises>1627128900</Rises>
              <Rises>1627181100</Rises>
              <Rises>1627195500</Rises>
              <SortMark>false</SortMark>
              <Schedule>
                  <Scheduled>true</Scheduled>
                  <Key>28</Key>
                  <Duration>1627114633</Duration>
                  <Duration>1627114633</Duration>
                  <Gap>104</Gap>
              </Schedule>
          </object>
          <object>
              <identifier>&#xA;&#x9;&#x9;&#x9;&#x9;J2022+2854&#xA;&#x9;&#x9;&#x9;</identifier>
              <ra>305.654</ra>
              <dec>28.9064</dec>
              <duration>0</duration>
              <weight>1</weight>
              <important>0</important>
              <Rises>1627114800</Rises>
              <Rises>1627129200</Rises>
              <Rises>1627181400</Rises>
              <Rises>1627195800</Rises>
              <SortMark>false</SortMark>
              <Schedule>
                  <Scheduled>true</Scheduled>
                  <Key>27</Key>
                  <Duration>1627115037</Duration>
                  <Duration>1627115037</Duration>
                  <Gap>2</Gap>
              </Schedule>
          </object>
          <object>
              <identifier>&#xA;&#x9;&#x9;&#x9;&#x9;J0034-0721&#xA;&#x9;&#x9;&#x9;</identifier>
              <ra>8.53712</ra>
              <dec>-7.36556</dec>
              <duration>0</duration>
              <weight>1</weight>
              <important>0</important>
              <Rises>1627116000</Rises>
              <Rises>1627138500</Rises>
              <SortMark>false</SortMark>
              <Schedule>
                  <Scheduled>true</Scheduled>
                  <Key>14</Key>
                  <Duration>1627116239</Duration>
                  <Duration>1627116239</Duration>
                  <Gap>594</Gap>
              </Schedule>
          </object>
          <object>
              <identifier>&#xA;&#x9;&#x9;&#x9;&#x9;J0332+5434&#xA;&#x9;&#x9;&#x9;</identifier>
              <ra>53.2473</ra>
              <dec>54.5792</dec>
              <duration>0</duration>
              <weight>1</weight>
              <important>0</important>
              <Rises>1627118100</Rises>
              <Rises>1627157700</Rises>
              <SortMark>false</SortMark>
              <Schedule>
                  <Scheduled>true</Scheduled>
                  <Key>12</Key>
                  <Duration>1627118333</Duration>
                  <Duration>1627118333</Duration>
                  <Gap>103</Gap>
              </Schedule>
          </object>
          <object>
              <identifier>&#xA;&#x9;&#x9;&#x9;&#x9;J0323+3944&#xA;&#x9;&#x9;&#x9;</identifier>
              <ra>50.8609</ra>
              <dec>39.748</dec>
              <duration>0</duration>
              <weight>1</weight>
              <important>0</important>
              <Rises>1627119000</Rises>
              <Rises>1627135200</Rises>
              <Rises>1627139400</Rises>
              <Rises>1627155600</Rises>
              <SortMark>false</SortMark>
              <Schedule>
                  <Scheduled>true</Scheduled>
                  <Key>12</Key>
                  <Duration>1627119036</Duration>
                  <Duration>1627119036</Duration>
                  <Gap>24</Gap>
              </Schedule>
          </object>
          <object>
              <identifier>&#xA;&#x9;&#x9;&#x9;&#x9;J0358+5413&#xA;&#x9;&#x9;&#x9;</identifier>
              <ra>59.7238</ra>
              <dec>54.2205</dec>
              <duration>0</duration>
              <weight>1</weight>
              <important>0</important>
              <Rises>1627119600</Rises>
              <Rises>1627159200</Rises>
              <SortMark>false</SortMark>
              <Schedule>
                  <Scheduled>true</Scheduled>
                  <Key>8</Key>
                  <Duration>1627119660</Duration>
                  <Duration>1627119660</Duration>
                  <Gap>24</Gap>
              </Schedule>
          </object>
          <object>
              <identifier>&#xA;&#x9;&#x9;&#x9;&#x9;J0454+5543&#xA;&#x9;&#x9;&#x9;</identifier>
              <ra>73.5321</ra>
              <dec>55.7282</dec>
              <duration>0</duration>
              <weight>1</weight>
              <important>0</important>
              <Rises>1627122900</Rises>
              <Rises>1627162800</Rises>
              <SortMark>false</SortMark>
              <Schedule>
                  <Scheduled>true</Scheduled>
                  <Key>14</Key>
                  <Duration>1627122984</Duration>
                  <Duration>1627122984</Duration>
                  <Gap>27</Gap>
              </Schedule>
          </object>
          <object>
              <identifier>&#xA;&#x9;&#x9;&#x9;&#x9;J0543+2329&#xA;&#x9;&#x9;&#x9;</identifier>
              <ra>85.7902</ra>
              <dec>23.485</dec>
              <duration>0</duration>
              <weight>1</weight>
              <important>0</important>
              <Rises>1627129200</Rises>
              <Rises>1627144500</Rises>
              <Rises>1627146600</Rises>
              <Rises>1627161900</Rises>
              <SortMark>false</SortMark>
              <Schedule>
                  <Scheduled>true</Scheduled>
                  <Key>5</Key>
                  <Duration>1627129311</Duration>
                  <Duration>1627129311</Duration>
                  <Gap>53</Gap>
              </Schedule>
          </object>
          <object>
              <identifier>&#xA;&#x9;&#x9;&#x9;&#x9;J0614+2229&#xA;&#x9;&#x9;&#x9;</identifier>
              <ra>93.5719</ra>
              <dec>22.5104</dec>
              <duration>0</duration>
              <weight>1</weight>
              <important>0</important>
              <Rises>1627131300</Rises>
              <Rises>1627163700</Rises>
              <SortMark>false</SortMark>
              <Schedule>
                  <Scheduled>true</Scheduled>
                  <Key>7</Key>
                  <Duration>1627131464</Duration>
                  <Duration>1627131464</Duration>
                  <Gap>15</Gap>
              </Schedule>
          </object>
          <object>
              <identifier>&#xA;&#x9;&#x9;&#x9;&#x9;J0814+7429&#xA;&#x9;&#x9;&#x9;</identifier>
              <ra>123.748</ra>
              <dec>74.4849</dec>
              <duration>0</duration>
              <weight>1</weight>
              <important>0</important>
              <Rises>1627131900</Rises>
              <Rises>1627177500</Rises>
              <SortMark>false</SortMark>
              <Schedule>
                  <Scheduled>true</Scheduled>
                  <Key>11</Key>
                  <Duration>1627132079</Duration>
                  <Duration>1627132079</Duration>
                  <Gap>86</Gap>
              </Schedule>
          </object>
          <object>
              <identifier>&#xA;&#x9;&#x9;&#x9;&#x9;J0629+2415&#xA;&#x9;&#x9;&#x9;</identifier>
              <ra>97.2739</ra>
              <dec>24.262</dec>
              <duration>0</duration>
              <weight>1</weight>
              <important>0</important>
              <Rises>1627131900</Rises>
              <Rises>1627146900</Rises>
              <Rises>1627149900</Rises>
              <Rises>1627164900</Rises>
              <SortMark>false</SortMark>
              <Schedule>
                  <Scheduled>true</Scheduled>
                  <Key>4</Key>
                  <Duration>1627132165</Duration>
                  <Duration>1627132165</Duration>
                  <Gap>83</Gap>
              </Schedule>
          </object>
          <object>
              <identifier>&#xA;&#x9;&#x9;&#x9;&#x9;J0452-1759&#xA;&#x9;&#x9;&#x9;</identifier>
              <ra>73.1421</ra>
              <dec>-17.9898</dec>
              <duration>0</duration>
              <weight>1</weight>
              <important>0</important>
              <Rises>1627134600</Rises>
              <Rises>1627150800</Rises>
              <SortMark>false</SortMark>
              <Schedule>
                  <Scheduled>true</Scheduled>
                  <Key>9</Key>
                  <Duration>1627134648</Duration>
                  <Duration>1627134648</Duration>
                  <Gap>70</Gap>
              </Schedule>
          </object>
          <object>
              <identifier>&#xA;&#x9;&#x9;&#x9;&#x9;J0659+1414&#xA;&#x9;&#x9;&#x9;</identifier>
              <ra>104.951</ra>
              <dec>14.2387</dec>
              <duration>0</duration>
              <weight>1</weight>
              <important>0</important>
              <Rises>1627135200</Rises>
              <Rises>1627165500</Rises>
              <SortMark>false</SortMark>
              <Schedule>
                  <Scheduled>true</Scheduled>
                  <Key>4</Key>
                  <Duration>1627135318</Duration>
                  <Duration>1627135318</Duration>
                  <Gap>63</Gap>
              </Schedule>
          </object>
          <object>
              <identifier>&#xA;&#x9;&#x9;&#x9;&#x9;J0826+2637&#xA;&#x9;&#x9;&#x9;</identifier>
              <ra>126.714</ra>
              <dec>26.623</dec>
              <duration>0</duration>
              <weight>1</weight>
              <important>0</important>
              <Rises>1627138800</Rises>
              <Rises>1627153200</Rises>
              <Rises>1627157700</Rises>
              <Rises>1627172100</Rises>
              <SortMark>false</SortMark>
              <Schedule>
                  <Scheduled>true</Scheduled>
                  <Key>4</Key>
                  <Duration>1627138981</Duration>
                  <Duration>1627138981</Duration>
                  <Gap>43</Gap>
              </Schedule>
          </object>
          <object>
              <identifier>&#xA;&#x9;&#x9;&#x9;&#x9;J0837+0610&#xA;&#x9;&#x9;&#x9;</identifier>
              <ra>129.274</ra>
              <dec>6.17071</dec>
              <duration>0</duration>
              <weight>1</weight>
              <important>0</important>
              <Rises>1627142100</Rises>
              <Rises>1627170000</Rises>
              <SortMark>false</SortMark>
              <Schedule>
                  <Scheduled>true</Scheduled>
                  <Key>3</Key>
                  <Duration>1627142324</Duration>
                  <Duration>1627142324</Duration>
                  <Gap>34</Gap>
              </Schedule>
          </object>
          <object>
              <identifier>&#xA;&#x9;&#x9;&#x9;&#x9;J0823+0159&#xA;&#x9;&#x9;&#x9;</identifier>
              <ra>125.791</ra>
              <dec>1.98682</dec>
              <duration>0</duration>
              <weight>1</weight>
              <important>0</important>
              <Rises>1627142100</Rises>
              <Rises>1627168500</Rises>
              <SortMark>false</SortMark>
              <Schedule>
                  <Scheduled>true</Scheduled>
                  <Key>0</Key>
                  <Duration>1627142358</Duration>
                  <Duration>1627142358</Duration>
                  <Gap>6</Gap>
              </Schedule>
          </object>
          <object>
              <identifier>&#xA;&#x9;&#x9;&#x9;&#x9;J0922+0638&#xA;&#x9;&#x9;&#x9;</identifier>
              <ra>140.559</ra>
              <dec>6.64133</dec>
              <duration>0</duration>
              <weight>1</weight>
              <important>0</important>
              <Rises>1627144800</Rises>
              <Rises>1627172700</Rises>
              <SortMark>false</SortMark>
              <Schedule>
                  <Scheduled>true</Scheduled>
                  <Key>1</Key>
                  <Duration>1627145064</Duration>
                  <Duration>1627145064</Duration>
                  <Gap>29</Gap>
              </Schedule>
          </object>
          <object>
              <identifier>&#xA;&#x9;&#x9;&#x9;&#x9;J0820-1350&#xA;&#x9;&#x9;&#x9;</identifier>
              <ra>125.11</ra>
              <dec>-13.849</dec>
              <duration>0</duration>
              <weight>1</weight>
              <important>0</important>
              <Rises>1627145700</Rises>
              <Rises>1627164600</Rises>
              <SortMark>false</SortMark>
              <Schedule>
                  <Scheduled>true</Scheduled>
                  <Key>2</Key>
                  <Duration>1627145993</Duration>
                  <Duration>1627145993</Duration>
                  <Gap>34</Gap>
              </Schedule>
          </object>
          <object>
              <identifier>&#xA;&#x9;&#x9;&#x9;&#x9;J0953+0755&#xA;&#x9;&#x9;&#x9;</identifier>
              <ra>148.289</ra>
              <dec>7.92678</dec>
              <duration>0</duration>
              <weight>1</weight>
              <important>0</important>
              <Rises>1627146300</Rises>
              <Rises>1627174800</Rises>
              <SortMark>false</SortMark>
              <Schedule>
                  <Scheduled>true</Scheduled>
                  <Key>0</Key>
                  <Duration>1627146327</Duration>
                  <Duration>1627146327</Duration>
                  <Gap>46</Gap>
              </Schedule>
          </object>
          <object>
              <identifier>&#xA;&#x9;&#x9;&#x9;&#x9;J1136+1551&#xA;&#x9;&#x9;&#x9;</identifier>
              <ra>174.013</ra>
              <dec>15.8543</dec>
              <duration>0</duration>
              <weight>1</weight>
              <important>0</important>
              <Rises>1627151400</Rises>
              <Rises>1627182300</Rises>
              <SortMark>false</SortMark>
              <Schedule>
                  <Scheduled>true</Scheduled>
                  <Key>15</Key>
                  <Duration>1627151473</Duration>
                  <Duration>1627151473</Duration>
                  <Gap>51</Gap>
              </Schedule>
          </object>
          <object>
              <identifier>&#xA;&#x9;&#x9;&#x9;&#x9;J1136+1551&#xA;&#x9;&#x9;&#x9;</identifier>
              <ra>174.013</ra>
              <dec>15.8543</dec>
              <duration>0</duration>
              <weight>1</weight>
              <important>0</important>
              <Rises>1627151400</Rises>
              <Rises>1627182300</Rises>
              <SortMark>false</SortMark>
              <Schedule>
                  <Scheduled>true</Scheduled>
                  <Key>10</Key>
                  <Duration>1627151524</Duration>
                  <Duration>1627151524</Duration>
                  <Gap>0</Gap>
              </Schedule>
          </object>
          <object>
              <identifier>&#xA;&#x9;&#x9;&#x9;&#x9;J1239+2453&#xA;&#x9;&#x9;&#x9;</identifier>
              <ra>189.918</ra>
              <dec>24.8972</dec>
              <duration>0</duration>
              <weight>1</weight>
              <important>0</important>
              <Rises>1627154100</Rises>
              <Rises>1627168800</Rises>
              <Rises>1627172400</Rises>
              <Rises>1627187100</Rises>
              <SortMark>false</SortMark>
              <Schedule>
                  <Scheduled>true</Scheduled>
                  <Key>10</Key>
                  <Duration>1627154224</Duration>
                  <Duration>1627154224</Duration>
                  <Gap>31</Gap>
              </Schedule>
          </object>
          <object>
              <identifier>&#xA;&#x9;&#x9;&#x9;&#x9;J1537+1155&#xA;&#x9;&#x9;&#x9;</identifier>
              <ra>234.292</ra>
              <dec>11.9321</dec>
              <duration>0</duration>
              <weight>1</weight>
              <important>0</important>
              <Rises>1627166400</Rises>
              <Rises>1627196100</Rises>
              <SortMark>false</SortMark>
              <Schedule>
                  <Scheduled>true</Scheduled>
                  <Key>3</Key>
                  <Duration>1627166555</Duration>
                  <Duration>1627166555</Duration>
                  <Gap>88</Gap>
              </Schedule>
          </object>
          <object>
              <identifier>&#xA;&#x9;&#x9;&#x9;&#x9;J1543+0929&#xA;&#x9;&#x9;&#x9;</identifier>
              <ra>235.912</ra>
              <dec>9.48792</dec>
              <duration>0</duration>
              <weight>1</weight>
              <important>0</important>
              <Rises>1627167300</Rises>
              <Rises>1627196100</Rises>
              <SortMark>false</SortMark>
              <Schedule>
                  <Scheduled>true</Scheduled>
                  <Key>4</Key>
                  <Duration>1627167543</Duration>
                  <Duration>1627167543</Duration>
                  <Gap>4</Gap>
              </Schedule>
          </object>
          <object>
              <identifier>&#xA;&#x9;&#x9;&#x9;&#x9;J1543-0620&#xA;&#x9;&#x9;&#x9;</identifier>
              <ra>235.876</ra>
              <dec>-6.3459</dec>
              <duration>0</duration>
              <weight>1</weight>
              <important>0</important>
              <Rises>1627170000</Rises>
              <Rises>1627193100</Rises>
              <SortMark>false</SortMark>
              <Schedule>
                  <Scheduled>true</Scheduled>
                  <Key>5</Key>
                  <Duration>1627170247</Duration>
                  <Duration>1627170247</Duration>
                  <Gap>26</Gap>
              </Schedule>
          </object>
          <object>
              <identifier>&#xA;&#x9;&#x9;&#x9;&#x9;J1607-0032&#xA;&#x9;&#x9;&#x9;</identifier>
              <ra>241.8</ra>
              <dec>-0.544675</dec>
              <duration>0</duration>
              <weight>1</weight>
              <important>0</important>
              <Rises>1627170300</Rises>
              <Rises>1627195800</Rises>
              <SortMark>false</SortMark>
              <Schedule>
                  <Scheduled>true</Scheduled>
                  <Key>3</Key>
                  <Duration>1627170573</Duration>
                  <Duration>1627170573</Duration>
                  <Gap>11</Gap>
              </Schedule>
          </object>
          <object>
              <identifier>&#xA;&#x9;&#x9;&#x9;&#x9;J1645-0317&#xA;&#x9;&#x9;&#x9;</identifier>
              <ra>251.258</ra>
              <dec>-3.29922</dec>
              <duration>0</duration>
              <weight>1</weight>
              <important>0</important>
              <Rises>1627110000</Rises>
              <Rises>1627111200</Rises>
              <Rises>1627173000</Rises>
              <Rises>1627196340</Rises>
              <SortMark>false</SortMark>
              <Schedule>
                  <Scheduled>true</Scheduled>
                  <Key>2</Key>
                  <Duration>1627173284</Duration>
                  <Duration>1627173284</Duration>
                  <Gap>18</Gap>
              </Schedule>
          </object>
          <object>
              <identifier>&#xA;&#x9;&#x9;&#x9;&#x9;J1730-2304&#xA;&#x9;&#x9;&#x9;</identifier>
              <ra>262.59</ra>
              <dec>-23.0754</dec>
              <duration>0</duration>
              <weight>1</weight>
              <important>0</important>
              <Rises>1627182600</Rises>
              <Rises>1627193400</Rises>
              <SortMark>false</SortMark>
              <Schedule>
                  <Scheduled>true</Scheduled>
                  <Key>4</Key>
                  <Duration>1627182602</Duration>
                  <Duration>1627182602</Duration>
                  <Gap>32</Gap>
              </Schedule>
          </object>
          <object>
              <identifier>&#xA;&#x9;&#x9;&#x9;&#x9;J1730-2304&#xA;&#x9;&#x9;&#x9;</identifier>
              <ra>262.59</ra>
              <dec>-23.0754</dec>
              <duration>0</duration>
              <weight>1</weight>
              <important>0</important>
              <Rises>1627182600</Rises>
              <Rises>1627193400</Rises>
              <SortMark>false</SortMark>
              <Schedule>
                  <Scheduled>true</Scheduled>
                  <Key>3</Key>
                  <Duration>1627182634</Duration>
                  <Duration>1627182634</Duration>
                  <Gap>0</Gap>
              </Schedule>
          </object>
          <object>
              <identifier>&#xA;&#x9;&#x9;&#x9;&#x9;J1730-2304&#xA;&#x9;&#x9;&#x9;</identifier>
              <ra>262.59</ra>
              <dec>-23.0754</dec>
              <duration>0</duration>
              <weight>1</weight>
              <important>0</important>
              <Rises>1627182600</Rises>
              <Rises>1627193400</Rises>
              <SortMark>false</SortMark>
              <Schedule>
                  <Scheduled>true</Scheduled>
                  <Key>2</Key>
                  <Duration>1627182634</Duration>
                  <Duration>1627182634</Duration>
                  <Gap>0</Gap>
              </Schedule>
          </object>
      </sources>
  </scheduller>